scancode_glc_plugin/__init__.py
scancode_glc_plugin/pipelines/__init__.py
scancode_glc_plugin/pipelines/glc_scan.py
scancode_glc_plugin/pipes/__init__.py
scancode_glc_plugin/pipes/glc.py
scancodeio_glc_plugin-0.0.2.dist-info/AUTHORS.rst
scancodeio_glc_plugin-0.0.2.dist-info/CHANGELOG.rst
scancodeio_glc_plugin-0.0.2.dist-info/METADATA
scancodeio_glc_plugin-0.0.2.dist-info/NOTICE
scancodeio_glc_plugin-0.0.2.dist-info/WHEEL
scancodeio_glc_plugin-0.0.2.dist-info/apache-2.0.LICENSE
scancodeio_glc_plugin-0.0.2.dist-info/entry_points.txt
scancodeio_glc_plugin-0.0.2.dist-info/top_level.txt
scancodeio_glc_plugin-0.0.2.dist-info/RECORD
