Metadata-Version: 2.1
Name: scancodeio-glc-plugin
Version: 0.0.2
Summary: Google Licenseclassifier pipeline for ScanCode.io
Home-page: https://github.com/nexB/scancodeio.io-pipeline-glc_scan
Author: nexB. Inc. and others
Author-email: info@aboutcode.org
License: Apache-2.0
Keywords: utilities,scancodeio,pipelines
Platform: UNKNOWN
Classifier: Development Status :: 4 - Beta
Classifier: Intended Audience :: Developers
Classifier: Programming Language :: Python :: 3
Classifier: Programming Language :: Python :: 3 :: Only
Classifier: Topic :: Software Development
Classifier: Topic :: Utilities
Requires-Python: >=3.6
License-File: apache-2.0.LICENSE
License-File: NOTICE
License-File: AUTHORS.rst
License-File: CHANGELOG.rst
Requires-Dist: golicense-classifier (==0.0.16)
Provides-Extra: docs
Requires-Dist: Sphinx (>=3.3.1) ; extra == 'docs'
Requires-Dist: sphinx-rtd-theme (>=0.5.0) ; extra == 'docs'
Requires-Dist: doc8 (>=0.8.1) ; extra == 'docs'
Provides-Extra: testing
Requires-Dist: pytest (>=6) ; extra == 'testing'
Requires-Dist: pytest-xdist (>=2) ; extra == 'testing'
